transpydata/TransPy.py
transpydata/__init__.py
transpydata/__version__.py
transpydata/config/IConfigurable.py
transpydata/config/IDataService.py
transpydata/config/IProcessor.py
transpydata/config/IResourceAware.py
transpydata/config/LoggableMixin.py
transpydata/config/__init__.py
transpydata/config/datainput/IDataInput.py
transpydata/config/datainput/MysqlDataInput.py
transpydata/config/datainput/SQSDataInput.py
transpydata/config/datainput/__init__.py
transpydata/config/dataoutput/IDataOutput.py
transpydata/config/dataoutput/RequestDataOutput.py
transpydata/config/dataoutput/SQSDataOutput.py
transpydata/config/dataoutput/__init__.py
transpydata/config/dataprocess/IDataProcess.py
transpydata/config/dataprocess/NoneDataProcess.py
transpydata/config/dataprocess/TranslateDataProcess.py
transpydata/config/dataprocess/__init__.py
transpydata/util/__init__.py
transpydata/util/decorators.py
transpydata-0.4.2.dist-info/LICENSE
transpydata-0.4.2.dist-info/METADATA
transpydata-0.4.2.dist-info/WHEEL
transpydata-0.4.2.dist-info/top_level.txt
transpydata-0.4.2.dist-info/RECORD
