Metadata-Version: 2.1
Name: transpydata
Version: 0.4.2
Summary: Framework for managing migrations
Home-page: https://github.com/salpreh/transpydata
Author: salpreh
Author-email: salva.perez46@gmail.com
License: Apache 2.0
Platform: UNKNOWN
License-File: LICENSE
Requires-Dist: mysql-connector-python
Requires-Dist: requests
Requires-Dist: clinlog
